setup.py
binomial_gaus_distrib/Binomialdistribution.py
binomial_gaus_distrib/Gaussiandistribution.py
binomial_gaus_distrib/Generaldistribution.py
binomial_gaus_distrib/__init__.py
binomial_gaus_distrib.egg-info/PKG-INFO
binomial_gaus_distrib.egg-info/SOURCES.txt
binomial_gaus_distrib.egg-info/dependency_links.txt
binomial_gaus_distrib.egg-info/not-zip-safe
binomial_gaus_distrib.egg-info/top_level.txt