Metadata-Version: 1.0
Name: binomial-gaus-distrib
Version: 1.1
Summary: Gaussian distributions
Home-page: UNKNOWN
Author: Rahul Gupta
Author-email: 385.rahul@gmail.com
License: UNKNOWN
Platform: UNKNOWN
